wledataloader/__init__.py
wledataloader/base_loader.py
wledataloader/colorado_loader.py
wledataloader/iecwle24_loader.py
wledataloader/jsi_sigfox_loader.py
wledataloader/pktmeta_loader.py
wledataloader/rutgers_loader.py
wledataloader/utils.py
wledataloader-0.1.1.dist-info/METADATA
wledataloader-0.1.1.dist-info/WHEEL
wledataloader-0.1.1.dist-info/top_level.txt
wledataloader-0.1.1.dist-info/RECORD
